<?xml version="1.0" encoding="UTF-8"?>
<objects serializationModel="Studio.02.00.00">
	<object class="AudioFile" id="{6345715e-f797-44c6-89af-0669bca3f2a9}">
		<property name="assetPath">
			<value>ESE - FIGHT PACK - HIT - Tight 06.wav</value>
		</property>
		<property name="frequencyInKHz">
			<value>48</value>
		</property>
		<property name="channelCount">
			<value>1</value>
		</property>
		<property name="length">
			<value>0.39583333333333331</value>
		</property>
		<relationship name="masterAssetFolder">
			<destination>{b936d5e9-6a52-4d3c-8f18-91c885339337}</destination>
		</relationship>
	</object>
</objects>
